setup.py
planet_LB/__init__.py
planet_LB/constants.py
planet_LB/planet_LB.py
planet_LB.egg-info/PKG-INFO
planet_LB.egg-info/SOURCES.txt
planet_LB.egg-info/dependency_links.txt
planet_LB.egg-info/top_level.txt