Metadata-Version: 2.1
Name: planet-LB
Version: 1.0.0
Summary: Lattice Boltzmann Solver for python
Home-page: UNKNOWN
Author: Craig O'Neill
License: UNKNOWN
Platform: UNKNOWN
